MANIFEST.in
README.rst
setup.py
ecopy/__init__.py
ecopy/test_ecopy_unittest.py
ecopy/utils.py
ecopy.egg-info/PKG-INFO
ecopy.egg-info/SOURCES.txt
ecopy.egg-info/dependency_links.txt
ecopy.egg-info/requires.txt
ecopy.egg-info/top_level.txt
ecopy/base_funcs/__init__.py
ecopy/base_funcs/impute.py
ecopy/base_funcs/spatial_median.py
ecopy/base_funcs/wt_mean.py
ecopy/base_funcs/wt_scale.py
ecopy/base_funcs/wt_var.py
ecopy/diversity/__init__.py
ecopy/diversity/beta_dispersion.py
ecopy/diversity/div_partition.py
ecopy/diversity/diversity.py
ecopy/diversity/rarefy.py
ecopy/matrix_comp/__init__.py
ecopy/matrix_comp/anosim.py
ecopy/matrix_comp/cca.py
ecopy/matrix_comp/ccor.py
ecopy/matrix_comp/fourthcorner.py
ecopy/matrix_comp/mantel.py
ecopy/matrix_comp/procrust_test.py
ecopy/matrix_comp/rda.py
ecopy/matrix_comp/rlq.py
ecopy/matrix_comp/simper.py
ecopy/ordination/__init__.py
ecopy/ordination/correspondance.py
ecopy/ordination/distance.py
ecopy/ordination/hillsmith.py
ecopy/ordination/mds.py
ecopy/ordination/ord_plot.py
ecopy/ordination/pca.py
ecopy/ordination/pcoa.py
ecopy/ordination/transform.py
ecopy/regression/__init__.py
ecopy/regression/isoFunc.c
ecopy/regression/isoFunc.pyx
ecopy/regression/isoregress.py
ecopy/regression/nls.py