Metadata-Version: 1.1
Name: ecopy
Version: 0.1.2.2
Summary: EcoPy: Ecological Data Analysis in Python
Home-page: https://github.com/Auerilas/ecopy
Author: Nathan Lemoine
Author-email: lemoine.nathan@gmail.com
License: MIT
Keywords: ordination,ecology,multivariate data analysis
Platform: UNKNOWN
Classifier: Development Status :: 3 - Alpha
Classifier: Intended Audience :: Science/Research
Classifier: License :: OSI Approved :: MIT License
Classifier: Programming Language :: Python :: 2.7
Classifier: Programming Language :: Python :: 3.4
